fastack_staticfiles/__init__.py
fastack_staticfiles-0.1.0.dist-info/LICENSE
fastack_staticfiles-0.1.0.dist-info/WHEEL
fastack_staticfiles-0.1.0.dist-info/METADATA
fastack_staticfiles-0.1.0.dist-info/RECORD
